geemlib/__init__.py
geemlib/geemlib.py
geemlib/Changelog/__init__.py
geemlib/Changelog/changelog.py
geemlib/Changelog/changelogEntry.py
geemlib/Changelog/version.py
geemlib/Web/WebBase.py
geemlib/Web/__init__.py
geemlib-1.0.3.dist-info/LICENSE
geemlib-1.0.3.dist-info/METADATA
geemlib-1.0.3.dist-info/WHEEL
geemlib-1.0.3.dist-info/entry_points.txt
geemlib-1.0.3.dist-info/top_level.txt
geemlib-1.0.3.dist-info/RECORD
